[
  {
    "slug": "2026-04-01",
    "title": "Energie Weekly – 2026-04-01",
    "date": "2026-04-01",
    "duration": "7:10",
    "summary": "Die Inflation in Österreich ist auf 3,1 Prozent gestiegen, während gleichzeitig die Netzgebühren durch ein neues Preismodell sinken. Europas Netzengpässe bedrohen 120 Gigawatt an geplanten Erneuerbare-Energien-Projekten. Batteriespeicher rücken als Schlüsseltechnologie ins Zentrum der Diskussion — neue Leitplanken der Bundesnetzagentur sollen Anreize schaffen.",
    "transcript": "Willkommen bei Energie Weekly, Ihrem Podcast für die neuesten und wichtigsten Nachrichten aus der Welt der Energie, des Klimas und der Nachhaltigkeit. Ich freue mich sehr, dass Sie heute wieder dabei sind und ich Ihnen einen umfassenden Überblick über die wichtigsten Entwicklungen der vergangenen Woche geben darf. Heute ist Mittwoch, der 1. April 2026, und es gibt wieder viel zu besprechen.\n\nBevor wir in die einzelnen Themen eintauchen, möchte ich Ihnen einen kurzen Überblick geben, was diese Woche besonders im Fokus stand. Die Inflationsrate in Österreich ist im März auf 3,1 Prozent gesprungen, und Experten warnen, dass dies erst der Anfang sein könnte. Gleichzeitig gibt es aber auch positive Entwicklungen bei den Energiepreisen: Ein neues Preismodell reduziert die Netzgebühren, was für Haushalte und Unternehmen spürbare Entlastungen bringen soll. Diese zwei seemingly gegensätzlichen Entwicklungen zeigen, wie komplex die aktuelle Energielandschaft ist.\n\nDas erste große Thema dieser Woche dreht sich um die Frage der Energieabhängigkeit Österreichs von fossilen Brennstoffen. Eine aktuelle Analyse zeigt, wie sich Österreich systematisch aus dieser Abhängigkeit befreien kann. Die Wege sind vielfältig und erfordern koordinierte Anstrengungen in mehreren Bereichen: dem Ausbau erneuerbarer Energien, der Modernisierung der Netzinfrastruktur, der Einführung intelligenter Stromtarife und der Förderung von Energieeffizienz in Industrie und Privathaushalten.\n\nBesonders interessant ist in diesem Zusammenhang die Frage der Netzgebühren. Ab April gibt es ein neues Preismodell, das die Netzgebühren reduziert und damit die Gesamtkosten für Strom sinken lässt. Experten betonen jedoch, dass die tatsächlichen Ersparnisse je nach Verbrauchsprofil und Region unterschiedlich ausfallen werden. Für einen durchschnittlichen Haushalt könnten die Ersparnisse bei mehreren hundert Euro pro Jahr liegen, doch in manchen Fällen könnten die Änderungen auch minimal ausfallen.\n\nWechseln wir nun zu einem Thema, das in Europa zunehmend Besorgnis erregt: Die Netzengpässe, die bis zu 120 Gigawatt an geplanten Erneuerbare-Energien-Projekten bedrohen. Diese enorme Menge an geplanten Solar- und Windkraftanlagen wartet auf einen Netzanschluss, doch die bestehende Infrastruktur ist vielerorts nicht ausreichend. Die Verzögerungen bei Genehmigungen und beim Netzausbau führen dazu, dass Projekte verschoben oder sogar aufgegeben werden müssen.\n\nDie Bundesnetzagentur hat als Reaktion auf diese Situation erste Leitplanken zu den Netzentgelten für Batteriespeicher vorgestellt. Diese Regelungen sollen Anreize schaffen, damit Speicherkapazitäten dort geschaffen werden, wo sie am meisten zur Netzstabilität beitragen. Batteriespeicher können eine wichtige Rolle dabei spielen, die Schwankungen auszugleichen, die durch die wetterabhängige Stromerzeugung aus Solar- und Windkraft entstehen.\n\nEin weiteres interessantes Phänomen, das diese Woche diskutiert wurde, ist die Rückkehr negativer Strompreise. Im Februar gab es mehrere Stunden, in denen der Strompreis an der Börse unter null fiel. Das klingt zunächst nach einem günstigen Geschäft für Verbraucher, hat aber auch Schattenseiten. Negative Preise entstehen, wenn zu viel Strom im Netz ist und nicht schnell genug abgenommen oder gespeichert werden kann. Für Batteriebetreiber können solche Phasen sowohl eine Chance als auch ein Risiko darstellen.\n\nEine neue Studie, die diese Woche vorgestellt wurde, analysiert die Auswirkungen negativer Preise auf die Erlöse von Batteriespeichern. Die Ergebnisse zeigen, dass die Erlöse im Februar 2026 zwar unter dem Niveau des Vorjahres lagen, Batteriespeicher aber nach wie vor eine wichtige Einnahmequelle für ihre Betreiber darstellen. Die Kombination aus Arbitrage-Geschäften und der Bereitstellung von Regelenergie kann auch in Zeiten niedriger Preise profitabel sein.\n\nAus Deutschland kommt die Meldung, dass Solar Fabrik ein neuartiges Solarpanel vorgestellt hat. Das rot-braune Modul fügt sich ästhetisch besser in das Stadtbild ein als herkömmliche dunkle Solarmodule und könnte damit neue Anwendungsfelder erschließen, insbesondere in städtischen Gebieten, wo die Optik oft ein Hindernis für die Installation von Solaranlagen darstellt.\n\nEin etwas ungewöhnliches Thema sorgte diese Woche für Aufmerksamkeit: Fake News als angebliche Vorboten einer neuen Gründerzeit in der Solarbranche in Berlin. Eine Analyse zeigt, wie Desinformation und überzogene Versprechen kurzfristig zu einem Boom geführt haben, der nun von Ernüchterung und Konsolidierung abgelöst wird. Solche Wellen sind in aufstrebenden Märkten nicht ungewöhnlich, zeigen aber, wie wichtig eine faktenbasierte Berichterstattung ist.\n\nBevor wir zum Ende kommen, möchte ich noch einen Blick auf die internationalen Entwicklungen werfen. Die globalen Energiemärkte bleiben volatil, und die Preisschwankungen bei Öl und Gas haben weiterhin Auswirkungen auf die Wirtschaft weltweit. Gleichzeitig beschleunigen viele Länder ihre Bemühungen um den Ausbau erneuerbarer Energien, angetrieben sowohl von Klimazielen als auch von wirtschaftlichen Überlegungen.\n\nDie Inflation in Österreich ist also auf 3,1 Prozent gesprungen, und das ist ein Anstieg, der viele Haushalte und Unternehmen beunruhigen wird. Doch gerade im Energiebereich gibt es gleichzeitig Licht und Schatten. Während die allgemeine Teuerung die Kosten für nahezu alle Güter steigen lässt, zeigt sich bei den Energiepreisen ein differenziertes Bild. Einerseits sind die Strompreise an den Börsen in den letzten Monaten gesunken, was theoretisch für günstigere Tarife für Endverbraucher sorgen sollte. Andererseits sind die Netzgebühren und Abgaben in vielen Fällen gestiegen, was den Gesamtpreis für Strom für Haushalte trotz niedrigerer Börsenpreise stabil gehalten oder sogar erhöht hat.\n\nDie Analyse, wie sich Österreich aus der Abhängigkeit von Öl und Gas befreien kann, ist besonders relevant in diesem Zusammenhang. Fossile Brennstoffe sind nicht nur eine Quelle für Treibhausgasemissionen, sondern auch ein geopolitisches Risiko, wie die Krisen der letzten Jahre gezeigt haben. Österreich hat in den vergangenen Jahren zwar Fortschritte beim Ausbau erneuerbarer Energien gemacht, doch der Weg zur vollständigen Unabhängigkeit von fossilen Energieträgern ist noch lang.\n\nBesonders die Frage der Wärmeversorgung bleibt eine große Herausforderung. Während im Stromsektor die erneuerbaren Energien bereits einen bedeutenden Anteil ausmachen, ist der Wärmesektor noch stark von Gas und Öl abhängig. Hier braucht es massive Investitionen in Wärmepumpen, Fernwärme und Gebäudesanierungen, um die Abhängigkeit zu reduzieren. Die aktuellen Preissignale, sowohl bei den Netzgebühren als auch bei den fossilen Brennstoffen, sollten hier als zusätzlicher Anreiz für Haushalte und Unternehmen dienen, in effizientere und sauberere Heizlösungen zu investieren.\n\nDie Situation bei den Netzengpässen in Europa bleibt dramatisch. Mit 120 Gigawatt an geplanten Erneuerbare-Energien-Projekten, die auf einen Netzanschluss warten, droht ein erheblicher Verlust an potenzieller sauberer Stromerzeugung. Diese Verzögerungen sind das Ergebnis komplexer Genehmigungsverfahren, unzureichender Investitionen in die Netzinfrastruktur und manchmal auch politischer Blockaden. Die Kosten für den Ausbau und die Modernisierung der Netze sind enorm, doch ohne diese Investitionen wird der Übergang zu einer CO2-freien Energieversorgung nicht gelingen.\n\nDie Bundesnetzagentur hat mit ihren Leitplanken zu den Netzentgelten für Batteriespeicher einen wichtigen Schritt getan, um die Rahmenbedingungen für Speichertechnologien zu klären. Batteriespeicher sind ein Schlüsselbaustein der Energiewende, da sie die volatile Einspeisung aus Solar- und Windkraft ausgleichen können. Mit der neuen Regelung sollen Anreize geschaffen werden, damit Speicher dort gebaut werden, wo sie für das Netz am wertvollsten sind, und nicht nur dort, wo es gerade die größten staatlichen Förderungen gibt.\n\nDie Rückkehr negativer Strompreise im Februar ist ein Symptom der zunehmenden Bedeutung erneuerbarer Energien im Strommix. Wenn die Sonne scheint und der Wind weht, kann an sonnigen und windy Tagen mehr Strom erzeugt werden als benötigt wird. Diese Überkapazität führt zu negativen Preisen an der Börse, da Erzeuger bereit sind, für die Einspeisung zu zahlen, anstatt ihre Anlagen abzuschalten. Für Verbraucher kann dies theoretisch bedeuten, dass sie zu bestimmten Zeiten gar keinen Strom bezahlen müssen — oder sogar dafür bezahlt bekommen, ihren Verbrauch zu flexibilisieren.\n\nDie neue Solarfabrik in Deutschland, die optisch ansprechendere Solarmodule entwickelt hat, zeigt, dass die Innovation in der Photovoltaikbranche nicht nur bei der Effizienz, sondern auch bei der Ästhetik ankommt. Traditionelle Solarmodule mit ihrer typischen dunklen Farbe und dem gleichmäßigen Erscheinungsbild passen nicht immer gut in städtische Umgebungen oder den ländlichen Raum. Mit der Entwicklung von Solarpanelen in erdigen Tönen, die sich harmonischer in rooftops und Fassaden einfügen, könnte die Akzeptanz für Solaranlagen weiter steigen.\n\nDas war's für heute bei Energie Weekly. Ich hoffe, Sie hatten Spaß beim Zuhören und haben einige neue Erkenntnisse gewinnen können. Wenn Ihnen der Podcast gefällt, dann teilen Sie ihn gerne mit Freunden und Bekannten, die sich für Energie und Klimaschutz interessieren. Bis zur nächsten Episode wünsche ich Ihnen eine gute Woche und bleiben Sie informiert über die spannende Welt der Energie und des Klimas.",
    "audioFile": "2026-04-01.mp3",
    "sources": [
      {"title": "Inflation climbs to 3.1% in March", "url": "https://www.meezan.live/magazine/inflation-in-austria-2026/", "source": "Meezan"},
      {"title": "Inflation in Austria jumps to 3.1% in March, experts warn 'it's just the beginning'", "url": "https://www.meezan.live/magazine/inflation-in-austria-2026/", "source": "Meezan"},
      {"title": "The path to oil and gas independence: how Austria can break free from fossil fuels", "url": "https://www.meezan.live/magazine/austria-energy-independence/", "source": "Meezan"},
      {"title": "Exploring Austria's renewable energy landscape in 2026", "url": "https://www.meezan.live/magazine/austria-renewable-energy/", "source": "Meezan"},
      {"title": "Renewable energy transition: Austria's path to sustainability", "url": "https://www.meezan.live/magazine/austria-energy-transition/", "source": "Meezan"}
    ]
  },
  {
    "slug": "2026-03-30",
    "title": "Energie Weekly – 30. März 2026",
    "date": "2026-03-30",
    "duration": "7:44",
    "summary": "Die Inflation in Österreich ist auf 3,1 Prozent gestiegen, während gleichzeitig die Netzgebühren durch ein neues Preismodell sinken. Europas Netzengpässe bedrohen 120 Gigawatt an geplanten Erneuerbare-Energien-Projekten. Batteriespeicher rücken als Schlüsseltechnologie ins Zentrum der Diskussion — neue Leitplanken der Bundesnetzagentur sollen Anreize schaffen.",
    "transcript": "Willkommen bei Energie Weekly...",
    "audioFile": "2026-03-30.mp3",
    "sources": []
  }
]
